{
  "data": {
    "identifier": "https://www.kaggle.com/datasets/adityakadiwal/water-potability",
    "identifierType": "URL",
    "attributes": {
      "doi": [],
      "creators": [
        {
          "creatorName": "Kadiwal, Aditya",
          "nameType": "Personal",
          "givenName": "Aditya",
          "familyName": "Kadiwal",
          "nameIdentifiers": [
            {
              "nameIdentifier": [],
              "nameIdentifierScheme": []
            }
          ],
          "affiliation": []
        }
      ],
      "titles": {
        "lang": "en",
        "title": "Water Quality"
      },
      "publisher": {
        "lang": "en",
        "name": "Kaggle",
        "schemeUri": "https://www.kaggle.com/"
      },
      "container": {},
      "publicationYear": 2021,
      "subjects": [
        {
          "subject": "Earth and Nature",
          "valueUri": "https://www.kaggle.com/datasets?tags=7000-Earth+and+Nature",
          "subjectScheme": "Kaggle Dataset Tags"
        },
        {
          "subject": "Beginner",
          "valueUri": "https://www.kaggle.com/datasets?tags=13102-Beginner",
          "subjectScheme": "Kaggle Dataset Tags"
        },
        {
          "subject": "Energy",
          "valueUri": "https://www.kaggle.com/datasets?tags=12016-Energy",
          "subjectScheme": "Kaggle Dataset Tags"
        },
        {
          "subject": "Public Health",
          "valueUri": "https://www.kaggle.com/datasets?tags=4309-Public+Health",
          "subjectScheme": "Kaggle Dataset Tags"
        },
        {
          "subject": "Environment",
          "valueUri": "https://www.kaggle.com/datasets?tags=7302-Environment",
          "subjectScheme": "Kaggle Dataset Tags"
        },
        {
          "subject": "Binary Classification",
          "valueUri": "https://www.kaggle.com/datasets?tags=14201-Binary+Classification",
          "subjectScheme": "Kaggle Dataset Tags"
        },
        {
          "subject": "Water Bodies",
          "valueUri": "https://www.kaggle.com/datasets?tags=3003-Water+Bodies",
          "subjectScheme": "Kaggle Dataset Tags"
        }
      ],
      "language": "en",
      "types": {
        "ris": "DATA",
        "bibtex": "misc",
        "citeproc": "dataset",
        "schemaOrg": "Dataset",
        "resourceType": "Synthetic Data",
        "resourceTypeGeneral": "Dataset"
      },
      "relatedIdentifiers": [
        {
          "relationType": "IsCitedBy",
          "relatedIdentifier": "10.3390/w14213359",
          "resourceTypeGeneral": "JournalArticle",
          "relatedIdentifierType": "DOI"
        },
        {
          "relationType": "IsCitedBy",
          "relatedIdentifier": "10.2991/aebmr.k.220405.184",
          "resourceTypeGeneral": "JournalArticle",
          "relatedIdentifierType": "DOI"
        },
        {
          "relationType": "IsCitedBy",
          "relatedIdentifier": "10.21121/eab.1252167",
          "resourceTypeGeneral": "JournalArticle",
          "relatedIdentifierType": "DOI"
        }
      ],
      "relatedItems": [],
      "sizes": [
        "257 KB",
        "525 KB"
      ],
      "formats": [
        "application/json"
      ],
      "rightsList": [
        {
          "lang": "en",
          "rights": "Creative Commons Zero v1.0 Universal",
          "rightsUri": "https://creativecommons.org/publicdomain/zero/1.0/deed.en",
          "schemeUri": "https://spdx.org/licenses/",
          "rightsIdentifier": "cc0-1.0",
          "rightsIdentifierScheme": "SPDX"
        }
      ]
    }
  }
}
